{
  "html_attributions" : [],
  "result" : {
    "address_components" : [
      {
        "long_name" : "41",
        "short_name" : "41",
        "types" : [ "street_number" ]
      },
      {
        "long_name" : "Rue de Paradis",
        "short_name" : "Rue de Paradis",
        "types" : [ "route" ]
      },
      {
        "long_name" : "Paris",
        "short_name" : "Paris",
        "types" : [ "locality", "political" ]
      },
      {
        "long_name" : "Paris",
        "short_name" : "Paris",
        "types" : [ "administrative_area_level_2", "political" ]
      },
      {
        "long_name" : "Île-de-France",
        "short_name" : "Île-de-France",
        "types" : [ "administrative_area_level_1", "political" ]
      },
      {
        "long_name" : "France",
        "short_name" : "FR",
        "types" : [ "country", "political" ]
      },
      {
        "long_name" : "75010",
        "short_name" : "75010",
        "types" : [ "postal_code" ]
      }
    ],
    "adr_address" : "\u003cspan class=\"street-address\"\u003e41 Rue de Paradis\u003c/span\u003e, \u003cspan class=\"postal-code\"\u003e75010\u003c/span\u003e \u003cspan class=\"locality\"\u003eParis\u003c/span\u003e, \u003cspan class=\"country-name\"\u003eFrance\u003c/span\u003e",
    "formatted_address" : "41 Rue de Paradis, 75010 Paris, France",
    "formatted_phone_number" : "01 53 34 00 64",
    "geometry" : {
      "location" : {
        "lat" : 48.8754079,
        "lng" : 2.3500513
      },
      "viewport" : {
        "northeast" : {
          "lat" : 48.8767947802915,
          "lng" : 2.351415630291501
        },
        "southwest" : {
          "lat" : 48.8740968197085,
          "lng" : 2.348717669708498
        }
      }
    },
    "icon" : "https://maps.gstatic.com/mapfiles/place_api/icons/restaurant-71.png",
    "id" : "2b0d73199d8860ea7ed3e1d66d851868b9653faf",
    "international_phone_number" : "+33 1 53 34 00 64",
    "name" : "Tesoro d'Italia",
    "opening_hours" : {
      "open_now" : true,
      "periods" : [
        {
          "close" : {
            "day" : 1,
            "time" : "1500"
          },
          "open" : {
            "day" : 1,
            "time" : "1200"
          }
        },
        {
          "close" : {
            "day" : 1,
            "time" : "2300"
          },
          "open" : {
            "day" : 1,
            "time" : "1830"
          }
        },
        {
          "close" : {
            "day" : 2,
            "time" : "1500"
          },
          "open" : {
            "day" : 2,
            "time" : "1200"
          }
        },
        {
          "close" : {
            "day" : 2,
            "time" : "2300"
          },
          "open" : {
            "day" : 2,
            "time" : "1830"
          }
        },
        {
          "close" : {
            "day" : 3,
            "time" : "1500"
          },
          "open" : {
            "day" : 3,
            "time" : "1200"
          }
        },
        {
          "close" : {
            "day" : 3,
            "time" : "2300"
          },
          "open" : {
            "day" : 3,
            "time" : "1830"
          }
        },
        {
          "close" : {
            "day" : 4,
            "time" : "1500"
          },
          "open" : {
            "day" : 4,
            "time" : "1200"
          }
        },
        {
          "close" : {
            "day" : 4,
            "time" : "2300"
          },
          "open" : {
            "day" : 4,
            "time" : "1830"
          }
        },
        {
          "close" : {
            "day" : 5,
            "time" : "1500"
          },
          "open" : {
            "day" : 5,
            "time" : "1200"
          }
        },
        {
          "close" : {
            "day" : 5,
            "time" : "2300"
          },
          "open" : {
            "day" : 5,
            "time" : "1830"
          }
        },
        {
          "close" : {
            "day" : 6,
            "time" : "1230"//vraie heure 1500
          },
          "open" : {
            "day" : 6,
            "time" : "1200"//vraie heure 1200
          }
        },
        {
          "close" : {
            "day" : 6,
            "time" : "2300"
          },
          "open" : {
            "day" : 6,
            "time" : "1830"
          }
        }
      ],
      "weekday_text" : [
        "Monday: 12:00 – 3:00 PM, 6:30 – 11:00 PM",
        "Tuesday: 12:00 – 3:00 PM, 6:30 – 11:00 PM",
        "Wednesday: 12:00 – 3:00 PM, 6:30 – 11:00 PM",
        "Thursday: 12:00 – 3:00 PM, 6:30 – 11:00 PM",
        "Friday: 12:00 – 3:00 PM, 6:30 – 11:00 PM",
        "Saturday: 12:00 – 3:00 PM, 6:30 – 11:00 PM",
        "Sunday: Closed"
      ]
    },
    "photos" : [
      {
        "height" : 1536,
        "html_attributions" : [
          "\u003ca href=\"https://maps.google.com/maps/contrib/106016015299106957568/photos\"\u003eMiya S.\u003c/a\u003e"
        ],
        "photo_reference" : "CmRaAAAAZP3thyoPMfqQzS0GMq1HnOJk75TkQCvnNdeZGYD5PaFgPW6Hpr33wJX99wiMnnT6nqhZrvCzdsUqokPDVhrX7fPv05w8OYGYv_8Hey5rgAQsffD5SKED1rhNtHLbGL0oEhCtzdOwlcZ4ODimbvmoXZL6GhSK7iLyqIErTbkuyFl6l3O64utpHw",
        "width" : 2048
      },
      {
        "height" : 2268,
        "html_attributions" : [
          "\u003ca href=\"https://maps.google.com/maps/contrib/115954145878917534624/photos\"\u003eDjagane Rattinavelou\u003c/a\u003e"
        ],
        "photo_reference" : "CmRaAAAAmSE4JJF1i1EOIxaqmuGHe_p_4qXAakUoxOCiTK5RX9UVD_mCvqLD-J232DlGZYpYQQynj7d7ehJx4Mx1kudyLyAMXp7jGrlebk9Ve6Hq4hDs3UuiT3Q5AkGABl-r2t1uEhBk08g3PFkPuavgDw9MFzMSGhShmRmtma_vRpVBoZ6qR-v5WvEtew",
        "width" : 4032
      },
      {
        "height" : 1960,
        "html_attributions" : [
          "\u003ca href=\"https://maps.google.com/maps/contrib/104904851599921826513/photos\"\u003ed b\u003c/a\u003e"
        ],
        "photo_reference" : "CmRaAAAAOvL1820643uNVwLzLvWBHgwKqh7YnqbuYZ9W29fjHqQ6ASgo5lae19NrP_EmOuC21O5zl9KBuBNsTGk60G4NZRi3ZxEMKjjy7M329DUgF5RTpzS6tSg0xtmQGQLWkYblEhCn-6zoP_FMxfK2BoTbi1WdGhQ63ju7BofT8AoJHkVfLSOAaDSYEw",
        "width" : 4032
      },
      {
        "height" : 3024,
        "html_attributions" : [
          "\u003ca href=\"https://maps.google.com/maps/contrib/115398023442228982481/photos\"\u003eDidier Meert\u003c/a\u003e"
        ],
        "photo_reference" : "CmRaAAAAJvfe5Uo_UQw82mj8W2ACiNIGE17vQwEkfkHNYkhf9cF9rpfW5WKej3WdUpeYohI7P58wRtYYFSaw_mmK9Tz2M4OunZoipAGFNmwO-v0LwM4AXDHtmj0bEamcyH2jiLY8EhAwNk1188EnIUi56s24nyXOGhQY1AvhT3WSP3Anf5i5HGVkCR-_WQ",
        "width" : 4032
      },
      {
        "height" : 1960,
        "html_attributions" : [
          "\u003ca href=\"https://maps.google.com/maps/contrib/104904851599921826513/photos\"\u003ed b\u003c/a\u003e"
        ],
        "photo_reference" : "CmRaAAAAP_y6jf-tz8DCqDc9biePZJX_zfSI3DVJBkiMXxbQuR1vx-9SG4pEeU1ztz5dds9hQzj0BGRb1OQP26yv1O9ukVYTjkh4p78evokMGvM0atdsQ5mrhsSQVjxJf06hKkBwEhAdfKz134jeAzN9cWgvvH4vGhSVular9N5UzXWGm8KwvSo2AEnCWQ",
        "width" : 4032
      },
      {
        "height" : 3120,
        "html_attributions" : [
          "\u003ca href=\"https://maps.google.com/maps/contrib/113451230058230494053/photos\"\u003eGuillaume Sangay\u003c/a\u003e"
        ],
        "photo_reference" : "CmRaAAAAUqlmo-cL8WQKiaOG8UJAOJgWTIKDzL0FUb8U8u739tpvQ3ISBeir0ojvSx4hbMSwHhngxJ7ZM9PPap0qqwK-_7vPz6y8Uqa9T5zFx6R4z8C4mcnE4jRhJZznfEdN8KCaEhDpchkHLONw_2HNX1y3U8_OGhSIP-VTZSwkvcVzIyYlZW80j9J44g",
        "width" : 4160
      },
      {
        "height" : 2268,
        "html_attributions" : [
          "\u003ca href=\"https://maps.google.com/maps/contrib/115954145878917534624/photos\"\u003eDjagane Rattinavelou\u003c/a\u003e"
        ],
        "photo_reference" : "CmRaAAAAJ_ZY_64B7HGmbbHAwloGwgSF4AyW8B-3A7I_XYArd_8OBNMvbgxFS0Xty7bk0ymDUXxScKZIbY7yhzgwi63J6p2j_uPG6zagvITWQXkOt728xiUuZwVMhQ0gobUin_hLEhAsWfgFNR35Y6EX40PrPdckGhQ_FDRnowrANSqY44AOMSWKNEISdw",
        "width" : 4032
      },
      {
        "height" : 3024,
        "html_attributions" : [
          "\u003ca href=\"https://maps.google.com/maps/contrib/111789226002308728443/photos\"\u003eTerry Chui\u003c/a\u003e"
        ],
        "photo_reference" : "CmRaAAAAHmbO8hM1D2YZlXi02TYRwP3_Ulb_3XXpN10S55AOs5dg6Q5l6aWS0SKrAou-3Bw6nyA6eRZB__HUBiCL3tWBz6P_2XoeNq93XWXbmXnaO5WEX9E_LityuT5zG_u6X4BVEhCVPwp7dUNDDIPfHB-MbiwNGhTvZ5YU_NouMwE63lYHI3x4qw6ATg",
        "width" : 4032
      },
      {
        "height" : 2976,
        "html_attributions" : [
          "\u003ca href=\"https://maps.google.com/maps/contrib/116463705887759858864/photos\"\u003eray zhang\u003c/a\u003e"
        ],
        "photo_reference" : "CmRaAAAAlnkDeZhjFBHR7UqwK51r81gH1ZdMJRZobpfziyo8b2hw8MuL1R5zJllofvkG3LbfRq7bAnQ7X48D0KOIf4p7IrxLkqN39yYUYnKrmwkUr1kc4nnw88QD2E8GgHs-8EJxEhDWZGFB18oYU_lsk8zQzcQTGhSElHTz0-Btt93pjf5Brz5BlpGmyA",
        "width" : 3968
      },
      {
        "height" : 4032,
        "html_attributions" : [
          "\u003ca href=\"https://maps.google.com/maps/contrib/111789226002308728443/photos\"\u003eTerry Chui\u003c/a\u003e"
        ],
        "photo_reference" : "CmRaAAAAXEjs6LhU6lCpq0GLBIhB6LptGDIx78DUhRRhTX5DHE_MPQOCyTqsVdxpp_gmmLb_qls6At2Bud4RYCdLTKi5K9kVZBtffTbxqUcSjly5WTXzGogacltodd-oBX8BozjmEhDQbHICPP2JdZj3nUVs9TVTGhQjcrgc2TP7yQExwqn3sA9abTSjTQ",
        "width" : 3024
      }
    ],
    "place_id" : "ChIJv7JzxxRu5kcR4erzMX_tZi8",
    "plus_code" : {
      "compound_code" : "V9G2+52 Paris, France",
      "global_code" : "8FW4V9G2+52"
    },
    "price_level" : 2,
    "rating" : 4.4,
    "reference" : "ChIJv7JzxxRu5kcR4erzMX_tZi8",
    "reviews" : [
      {
        "author_name" : "Mika Lindblad",
        "author_url" : "https://www.google.com/maps/contrib/117797349707956273598/reviews",
        "language" : "en",
        "profile_photo_url" : "https://lh3.googleusercontent.com/-bNIon962-P0/AAAAAAAAAAI/AAAAAAAAAFo/zp5L1ATLc7c/s128-c0x00000000-cc-rp-mo/photo.jpg",
        "rating" : 5,
        "relative_time_description" : "2 months ago",
        "text" : "Amazing food for a very good price! Great service from helpful staff that spoke great English. Don't be fooled by the interior. This place is fantastic!",
        "time" : 1541715001
      },
      {
        "author_name" : "Randall Weeks",
        "author_url" : "https://www.google.com/maps/contrib/106265666118116064488/reviews",
        "language" : "en",
        "profile_photo_url" : "https://lh4.googleusercontent.com/-pvYPT7XEFW0/AAAAAAAAAAI/AAAAAAAAAD0/wu1rRxpTMqw/s128-c0x00000000-cc-rp-mo-ba2/photo.jpg",
        "rating" : 5,
        "relative_time_description" : "2 weeks ago",
        "text" : "Amazing food. The house red wine is legit. Fair prices and good portions. Yum!!",
        "time" : 1546110066
      },
      {
        "author_name" : "Mathew Mejia",
        "author_url" : "https://www.google.com/maps/contrib/114107484521934371713/reviews",
        "language" : "en",
        "profile_photo_url" : "https://lh5.googleusercontent.com/-rLPuu9r9ueg/AAAAAAAAAAI/AAAAAAAAHdM/0w1_2uRewyQ/s128-c0x00000000-cc-rp-mo-ba4/photo.jpg",
        "rating" : 5,
        "relative_time_description" : "4 months ago",
        "text" : "The food here was absolutely amazing. The staff was very friendly and worked very hard to accommodate us and make sure that we had everything that we needed. If you're on the fence about eating here, just come. You will not be disappointed.",
        "time" : 1535046975
      },
      {
        "author_name" : "Rafael Santos",
        "author_url" : "https://www.google.com/maps/contrib/102034189539900105795/reviews",
        "language" : "en",
        "profile_photo_url" : "https://lh3.googleusercontent.com/-xppRR5Qnlkc/AAAAAAAAAAI/AAAAAAAAF1U/wO3BwH7Vltc/s128-c0x00000000-cc-rp-mo-ba3/photo.jpg",
        "rating" : 5,
        "relative_time_description" : "a month ago",
        "text" : "Amazing food and price!",
        "time" : 1543491337
      },
      {
        "author_name" : "Carolina Gutierrez",
        "author_url" : "https://www.google.com/maps/contrib/113078873486471365806/reviews",
        "language" : "en",
        "profile_photo_url" : "https://lh4.googleusercontent.com/-ujdirPqer_E/AAAAAAAAAAI/AAAAAAAAAF0/MX7oVGme0ew/s128-c0x00000000-cc-rp-mo/photo.jpg",
        "rating" : 5,
        "relative_time_description" : "10 months ago",
        "text" : "Amazing food!!! My sister used Yelp and thought it looked good. Thankfully they were open until 11pm. The food did not disappointment! Highly recommended.",
        "time" : 1519558182
      }
    ],
    "scope" : "GOOGLE",
    "types" : [ "restaurant", "point_of_interest", "food", "establishment" ],
    "url" : "https://maps.google.com/?cid=3415678497961798369",
    "user_ratings_total" : 232,
    "utc_offset" : 60,
    "vicinity" : "41 Rue de Paradis, Paris",
    "website" : "http://tesoroditalia.com/"
  },
  "status" : "OK"
}